{
    "$schema": "http://schema.management.azure.com/schemas/2015-01-01/deploymentParameters.json#",
    "contentVersion": "1.0.0.0",
    "parameters": {
      "vmSku": {
        "value": "Standard_D4_v3"
      },
      "windowsOSVersion": {
        "value": "2016-Datacenter"
      },
      "vmssName": {
        "value": "VMSSDSC"
      },
      "instanceCount": {
        "value": 3
      },
      "adminUsername": {
        "value": "azureadmin"
      },
      "adminPassword": {
        "value": "J@ZUR3GR@V32018"
      }
    }
  }